{"artist":"alaa-abd-elkhalek","lyricsDownloaded":true,"songs":[{"lang":"Arabic","link":"https://lyricstranslate.com/en/alaa-abd-elkhalek-dary-lyrics.html","englishTranslations":[{"link":"https://lyricstranslate.com/en/dary-hide.html","id":"1248943","lyrics":[{"id":"0-1","text":"Hide your eyelashes from me and hide.. hide, hide"},{"id":"0-2","text":"\nWhy do you love amplifying my fire1.. hide, hide"},{"id":"1-1","text":"My heart has given itself up to you, a lover from the first instance,  The beauty of your eyes [even] needs not burn me"},{"id":"1-2","text":"\nThe arrow of your love is in my heart, your beauty is a miracle; if I attempted to conceal [it], my eyes betray my love [for you]"},{"id":"1-3","text":"\nand once again I tell you that my heart is melting in your love, it loves its life in your shadow and draws your eyes as my home"},{"id":"1-4","text":"\nWherever you take me [lie] the path and my days. Your love is my anchor; it calls my dreams"}],"title":"Hide"}],"id":"831170","transliteration":{"id":null,"lyrics":null,"title":null},"lyrics":[{"id":"0-1","text":"داري رموشك عني وداري ....داري داري"},{"id":"0-2","text":"\nليه بتحبي تزيدي في ناري ....ناري ناري "},{"id":"1-1","text":"قلبي مسلم ليكي عاشق من أولها مش محتاجه عنيكي تكويني بجمالها"},{"id":"1-2","text":"\nسهم هواكي بقلبي يالي جمالك أية لو فكرت أخبي عيني تبوح بهوايا"},{"id":"1-3","text":"\nوارجع تاني  و أقولك قلبي بحبك دايب عاشق عمره في ضيلك راسم عينك داري"},{"id":"1-4","text":"\nمطرح متوديني للسكة و أيامي حبك بيرسيني و ينادي لاحلامي"}],"title":"دارى"}]}