{
  "artist": "tarek-el-sheikh",
  "lyricsDownloaded": true,
  "songs": [
    {
      "lang": "Arabic",
      "link": "https://lyricstranslate.com/en/tarek-el-sheikh-nadam-omrak-lyrics.html",
      "englishTranslations": [
        {
          "link": "https://lyricstranslate.com/en/nadam-omrak-lifetime-remorse.html",
          "id": "543040",
          "lyrics": [
            { "id": "0-1", "text": "Remorse remorse remorse" },
            {
              "id": "0-2",
              "text": "\nYou will live your life feeling remorse"
            },
            { "id": "0-3", "text": "\nRemorse remorse remorse" },
            {
              "id": "0-4",
              "text": "\nAfter you leave me you will see woe and pain"
            },
            {
              "id": "0-5",
              "text": "\nA remorse as great as the love you wished for"
            },
            {
              "id": "0-6",
              "text": "\nA remorse as great as my suffering however it would be too late to know my value"
            },
            { "id": "0-7", "text": "\nThe coming days will be the proof" },
            {
              "id": "0-8",
              "text": "\nTomorrow you will come back with shame(broken eye)"
            },
            {
              "id": "0-9",
              "text": "\nWhen you suffer of loneliness and experience the  regret of your lifetime"
            },
            {
              "id": "0-10",
              "text": "\nRegret me and feel a little of my heart ache"
            },
            {
              "id": "0-11",
              "text": "\nDo not think that you fooled me with your lies"
            },
            {
              "id": "0-12",
              "text": "\nYou wanted me to burn in fire and never show pain"
            },
            {
              "id": "0-13",
              "text": "\nShowing up a little and disappear again and you want me to accept that and not to complain"
            },
            {
              "id": "0-14",
              "text": "\nI always came back and said OK even though I was suffering"
            },
            {
              "id": "0-15",
              "text": "\nI will never accept  this any more and be silent"
            },
            {
              "id": "0-16",
              "text": "\nI should have rejected it even if it killed me"
            },
            {
              "id": "0-17",
              "text": "\nWho wants to be just a shadow with no use"
            },
            {
              "id": "0-18",
              "text": "\nRegret who you are and learn to live free and be honest"
            },
            {
              "id": "0-19",
              "text": "\nWhy do you accept that and  cheapen yourself"
            },
            {
              "id": "0-20",
              "text": "\nLive clean(honest) for the rest of your life"
            },
            {
              "id": "0-21",
              "text": "\nI know your whole story and it is quite clear"
            },
            {
              "id": "0-22",
              "text": "\nI should have known what you are and wake up"
            },
            {
              "id": "0-23",
              "text": "\nYou are just someone who wants an easy life"
            },
            {
              "id": "0-24",
              "text": "\nSomeone who has no feelings of humanity"
            },
            {
              "id": "0-25",
              "text": "\nAll you know is for how much you can take me"
            },
            {
              "id": "0-26",
              "text": "\nYou compromise even though you believe it is a game"
            },
            {
              "id": "0-27",
              "text": "\nEvery thing you want you get nothing is difficult"
            },
            {
              "id": "0-28",
              "text": "\nI stood by you and you left my hugs and embrace"
            },
            {
              "id": "0-29",
              "text": "\nLife entertains you but your end is soon"
            },
            { "id": "0-30", "text": "\nI was kind but not any more" },
            {
              "id": "0-31",
              "text": "\nYou are breaking down night after night and insulting your heart"
            },
            {
              "id": "0-32",
              "text": "\nEach time your tears are fallen next to you"
            },
            {
              "id": "0-33",
              "text": "\nWhat forces me to love some one with no dignity"
            },
            {
              "id": "0-34",
              "text": "\nDo you think your gains  out of this path"
            },
            {
              "id": "0-35",
              "text": "\nwould add any  respect and  value to who you are"
            },
            {
              "id": "0-36",
              "text": "\nYou are someone I do not want to know and goodbye"
            },
            { "id": "1-1", "text": "ندم ندم ندم" },
            { "id": "1-2", "text": "\nهتعيش طول عمرك تحس بندم" },
            { "id": "1-3", "text": "\nندم ندم ندم" },
            { "id": "1-4", "text": "\nهتشوف من بعدى الويل والام" },
            { "id": "1-5", "text": "\nهتندم قد ما اتمنيت تصون الحب وتطبطب" },
            { "id": "1-6", "text": "\nهتندم قد ما انا قسيت وتعرف قيمتى متأخر" },
            { "id": "1-7", "text": "\nوالايام اهى بينى وبينك" },
            { "id": "1-8", "text": "\nبكرة هتيجى ومكسورة عينك" },
            { "id": "1-9", "text": "\nوالايام اهى بينى وبينك" },
            { "id": "1-10", "text": "\nبكرة هتيجى ومكسورة عينك" },
            {
              "id": "1-11",
              "text": "\nلما تأسى من الحرمان وتعيش كده ندمان ندم عمرك"
            },
            { "id": "1-12", "text": "\nاندم عليا ودوق عذاب قلبى شويه" },
            { "id": "1-13", "text": "\nاوعاك تفكر كدبتك دخلت عليا" },
            { "id": "1-14", "text": "\nعايزانى فى النار انطفى ولا يوم ابين" },
            { "id": "1-15", "text": "\nتظهر شويه وتختفى واسكت واسهين" },
            { "id": "1-16", "text": "\nوارجع واقول معلشى وانا اعيش فى ازمه" },
            { "id": "1-17", "text": "\nعمرى ما هقبل بلكلام ده وبسكوتى" },
            { "id": "1-18", "text": "\nكان لازم ارفض حتى لو كان فيها موتى" },
            { "id": "1-19", "text": "\nمين ده يقبل يبقى ضل ملوهش لزمه" },
            {
              "id": "1-20",
              "text": "\nندمان انك واياك تتعلم تعيش حر وتبقى شريف"
            },
            { "id": "1-21", "text": "\nبتهون على نفسك ليه ترخص نفسك" },
            { "id": "1-22", "text": "\nمتعيش باقى العمر نضيف" },
            { "id": "1-23", "text": "\nعارف حكايتك كلها والقصه واضحه" },
            { "id": "1-24", "text": "\nكان لازم اعرف انت ايه كان لازم اصحى" },
            { "id": "1-25", "text": "\nانت يا دوب حد وعايز سكه سهله" },
            { "id": "1-26", "text": "\nانسان ملهوش فى الانسانه مشاعرو جارة" },
            { "id": "1-27", "text": "\nكل الى عايزو وتعرفو بكام تاخدنى" },
            { "id": "1-28", "text": "\nعمال تراضى وانت راضى تبقى لعبه" },
            { "id": "1-29", "text": "\nكل الى عايزو بتلاقيه ولا حاجه صعبه" },
            { "id": "1-30", "text": "\nوقفت جنبك قد ايه وفارقت حضنى" },
            { "id": "2-1", "text": "ندمان انك واياك تتعلم تعيش حر وتبقى شريف" },
            { "id": "2-2", "text": "\nبتهون على نفسك ليه ترخص نفسك" },
            { "id": "2-3", "text": "\nمتعيش باقى العمر نضيف" },
            { "id": "2-4", "text": "\nالدنيا لهياك انما اخرك قريب" },
            { "id": "2-5", "text": "\nوانا كنت طيب بس انا مبقتش طيب" },
            { "id": "2-6", "text": "\nدى كل ليله بتنكسر وتهين فى قلبك" },
            { "id": "2-7", "text": "\nوكل مرة دمعتك مرميه جنبك" },
            { "id": "2-8", "text": "\nوانا ايه غاصبنى احب حد ملوش كرامه" },
            { "id": "2-9", "text": "\nهو انت فاكر مكسبك فى السكه ديا" },
            { "id": "2-10", "text": "\nهيخلى شكلك محترم ولو شويه" },
            { "id": "2-11", "text": "\nانسان خلاص مش هعرفك وبلسلامه" },
            { "id": "3-1", "text": "ندمان انك واياك تتعلم تعيش حر وتبقى شريف" },
            { "id": "3-2", "text": "\nبتهون على نفسك ليه ترخص نفسك" },
            { "id": "3-3", "text": "\nمتعيش باقى العمر نضيف" }
          ],
          "title": "Lifetime Remorse"
        }
      ],
      "id": "542865",
      "transliteration": { "id": null, "lyrics": null, "title": null },
      "lyrics": [
        {
          "id": "0-1",
          "text": "i couldn't find the text, there's the video of the song, i'm sorry"
        }
      ],
      "title": "NADAM OMRAK"
    },
    {
      "lang": "Arabic",
      "link": "https://lyricstranslate.com/en/cairokee-el-keef-%D8%A7%D9%84%D9%83%D9%8A%D9%81-lyrics.html",
      "englishTranslations": [
        {
          "link": "https://lyricstranslate.com/en/el-keef-%D8%A7%D9%84%D9%83%D9%8A%D9%81-rush.html",
          "id": "2383535",
          "lyrics": [
            { "id": "0-1", "text": "Damn you, rush, and damn knowing you" },
            {
              "id": "0-2",
              "text": "\nit's true you're a joy, but I wish I never knew you"
            },
            {
              "id": "0-3",
              "text": "\nat first you were great, crushing sorrows"
            },
            {
              "id": "0-4",
              "text": "\nnow I'm running away from myself and life"
            },
            {
              "id": "1-1",
              "text": "damn you, rush, you promised me a lot and then you ran away"
            },
            { "id": "1-2", "text": "\nI'm living lonely like a shadow" },
            { "id": "1-3", "text": "\nthere's a mother***** inside my head" },
            {
              "id": "1-4",
              "text": "\none who's an all around criminal, it's terrifying "
            },
            {
              "id": "2-1",
              "text": "a cigarette followed by a joint, a joint followed by a pill"
            },
            {
              "id": "2-2",
              "text": "\na pill followed by so many others until I can't move"
            },
            {
              "id": "2-3",
              "text": "\na cigarette followed by a joint, a joint followed by a pill"
            },
            {
              "id": "2-4",
              "text": "\na pill followed by so many others until I can't move"
            },
            { "id": "3-1", "text": "since that day, I haven't been myself" },
            { "id": "3-2", "text": "\npeople are moving on and I'm still" },
            { "id": "4-1", "text": "damn you, rush, you're humiliating me" },
            {
              "id": "4-2",
              "text": "\nin your absence I can't live and I can't find joy"
            },
            {
              "id": "4-3",
              "text": "\nIn a deep sleep, on the verge of a coma"
            },
            { "id": "4-4", "text": "\nand I can't seem to get up" },
            { "id": "5-1", "text": "damn you, rush, and damn your days" },
            {
              "id": "5-2",
              "text": "\nI wish I'd listened to people and not listened to you"
            },
            {
              "id": "5-3",
              "text": "\nI wish if life would solace me and a touch of kindness"
            },
            {
              "id": "5-4",
              "text": "\nand put my back that's been broken back together so I can return like the old days"
            },
            {
              "id": "6-1",
              "text": "a cigarette followed by a joint, a joint followed by a pill"
            },
            {
              "id": "6-2",
              "text": "\na pill followed by so many others until I can't move"
            },
            {
              "id": "6-3",
              "text": "\na cigarette followed by a joint, a joint followed by a pill"
            },
            {
              "id": "6-4",
              "text": "\na pill followed by so many others until I can't move"
            },
            { "id": "7-1", "text": "since that day, I haven't been myself" },
            { "id": "7-2", "text": "\npeople are moving on and I'm still" },
            {
              "id": "8-1",
              "text": "a cigarette followed by a joint, a joint followed by a pill"
            },
            {
              "id": "8-2",
              "text": "\na pill followed by so many others until I can't move"
            },
            {
              "id": "8-3",
              "text": "\na cigarette followed by a joint, a joint followed by a pill"
            },
            {
              "id": "8-4",
              "text": "\na pill followed by so many others until I can't move"
            }
          ],
          "title": "The Rush"
        }
      ],
      "id": "1784505",
      "transliteration": { "id": null, "lyrics": null, "title": null },
      "lyrics": [
        { "id": "0-1", "text": "يخرب بيتك يا كيف ويخرب بيت معرفتك" },
        { "id": "0-2", "text": "\nصحيح دمك خفيف بس يا ريتني ما عرفتك" },
        { "id": "0-3", "text": "\nفالأول كنت تمام بتدوس عالأحزان" },
        { "id": "0-4", "text": "\nدلوقتي أنا هربان من نفسي والأيام " },
        { "id": "1-1", "text": "يخرب بيتك يا كيف عشمتني وفلقت" },
        { "id": "1-2", "text": "\nعايش فالدنيا طيف ومليش فيها حد" },
        { "id": "1-3", "text": "\nفي واحد ابن حرام قاعد جوا نفوخي" },
        { "id": "1-4", "text": "\nواحد كله إجرام أه منه يا خوفي" },
        { "id": "2-1", "text": "وسيجارة جابت جوان وجوان جاب حباية" },
        { "id": "2-2", "text": "\nحباية جابت شريط وانتهت الحكاية" },
        { "id": "2-3", "text": "\nوسيجارة جابت جوان وجوان جاب حباية" },
        { "id": "2-4", "text": "\nحباية جابت شريط وانتهت الحكاية" },
        { "id": "3-1", "text": "من يومها وأنا أنا مش أنا" },
        { "id": "3-2", "text": "\nالناس راحت هناك وأنا مرمي هنا" },
        { "id": "4-1", "text": "يخرب بيتك يا كيف يا معيشني في مذلة" },
        { "id": "4-2", "text": "\nفي بعدك مش عارف أعيش ولا عارف أتهنى" },
        { "id": "4-3", "text": "\nنايم في سابع نومة وداخل في كوما" },
        { "id": "4-4", "text": "\nخلصانة ومش باينلي قومة" },
        { "id": "5-1", "text": "يخرب بيتك يا كيف ويخرب بيت أيامك" },
        { "id": "5-2", "text": "\nيا ريتني سمعت الناس ومسمعتش كلامك" },
        { "id": "5-3", "text": "\nوأجبر بخاطري يا زمن واديلي لمسة حنان" },
        { "id": "5-4", "text": "\nوافرد ضهري اللي اتقطم ورجعني زي زمان" },
        { "id": "6-1", "text": "وسيجارة جابت جوان وجوان جاب حباية" },
        { "id": "6-2", "text": "\nحباية جابت شريط وانتهت الحكاية" },
        { "id": "6-3", "text": "\nوسيجارة جابت جوان وجوان جاب حباية" },
        { "id": "6-4", "text": "\nحباية جابت شريط وانتهت الحكاية" },
        { "id": "7-1", "text": "من يومها وأنا أنا مش أنا" },
        { "id": "7-2", "text": "\nالناس راحت هناك وأنا مرمي هنا" },
        { "id": "8-1", "text": "وسيجارة جابت جوان وجوان جاب حباية" },
        { "id": "8-2", "text": "\nحباية جابت شريط وانتهت الحكاية" },
        { "id": "8-3", "text": "\nوسيجارة جابت جوان وجوان جاب حباية" },
        { "id": "8-4", "text": "\nحباية جابت شريط وانتهت الحكاية﻿" }
      ],
      "title": "الكيف"
    }
  ]
}
