{"artist":"ياسمين-الخيام","lyricsDownloaded":true,"songs":[{"lang":"Arabic","link":"https://lyricstranslate.com/en/ياسمين-الخيام-مبروك-عليكم-وعلينا-lyrics.html","englishTranslations":[{"link":"https://lyricstranslate.com/en/مبروك-عليكم-وعلينا-congratulations-you-and.html","id":"2795332","lyrics":[{"id":"0-1","text":"Congratulations ×3"},{"id":"0-2","text":"\nCongratulations for you and for us"},{"id":"0-3","text":"\nCongratulations ×3"},{"id":"0-4","text":"\nOh our family and people, congratulations"},{"id":"0-5","text":"\nOh God, give us more joys"},{"id":"0-6","text":"\nAnd reward us depending on our intention"},{"id":"1-1","text":"Oh how great is this happiness, it gathers the beloved ones"},{"id":"1-2","text":"\nAllah ×3"},{"id":"1-3","text":"\nAnd tonight is the happiest of our nights and because of the happiness, our hearts are young"},{"id":"1-4","text":"\nAllah ×3"},{"id":"1-5","text":"\nOh God, give us more joys"},{"id":"1-6","text":"\nAnd reward us depending on our intention"},{"id":"2-1","text":"Clap, clap come on"},{"id":"2-2","text":"\nGive a clap to the one who is makimg us happy"},{"id":"2-3","text":"\nAnd pray for him, may he live"},{"id":"2-4","text":"\nMay he live, may he live"},{"id":"2-5","text":"\nBelieve the ones who said before us"},{"id":"2-6","text":"\nThere is nothing more beautiful than tje happiness"},{"id":"2-7","text":"\nOh God, give us more joys"},{"id":"2-8","text":"\nAnd reward us depending on our intention"},{"id":"2-9","text":"\nCongratulations ×3"},{"id":"2-10","text":"\nCongratulations for you and for us"},{"id":"2-11","text":"\nCongratulations ×3"},{"id":"2-12","text":"\nOh our family and people, congratulations"},{"id":"2-13","text":"\nOh God, give us more joys"},{"id":"2-14","text":"\nAnd reward us depending on our intention"}],"title":"Congratulations For You and For Us"}],"id":"2777963","transliteration":{"id":null,"lyrics":null,"title":null},"lyrics":[{"id":"0-1","text":"مبروك مبروك مبرررروك"},{"id":"0-2","text":"\nمبروك عليكم وعلينا"},{"id":"0-3","text":"\nمبروك مبروك مبروووك"},{"id":"0-4","text":"\nمبروك يا ناسنا وأهالينا"},{"id":"0-5","text":"\nيارب كتر أفراحنا"},{"id":"0-6","text":"\nوعلى قد نيتنا إيدينا"},{"id":"1-1","text":"الله على الفرحة جميلة بتجمع شمل الأحباب"},{"id":"1-2","text":"\nالله الله الله"},{"id":"1-3","text":"\nوالليله أسعد ليالينا وقلوبنا من الفرحة شباب"},{"id":"1-4","text":"\nالله الله الله"},{"id":"1-5","text":"\nيارب كتر أفراحنا"},{"id":"1-6","text":"\nوعلى قد نيتنا إيدينا"},{"id":"2-1","text":"تصقيفة تصقيفة يلاااااااا"},{"id":"2-2","text":"\nتصقيفه للى يفرحنا"},{"id":"2-3","text":"\nوأدعوله إن شاء الله يعيش"},{"id":"2-4","text":"\nأن شاء الله يعيش إن شاء الله"},{"id":"2-5","text":"\nصدقوا اللى قالو قبلينا"},{"id":"2-6","text":"\nأجمل من الفرحه مفيش"},{"id":"2-7","text":"\nيارب كتر أفراحنا"},{"id":"2-8","text":"\nوعلى قد نيتنا إيدينا"},{"id":"2-9","text":"\nمبروك مبروك مبرررروك"},{"id":"2-10","text":"\nمبروك عليكم وعلينا"},{"id":"2-11","text":"\nمبروك مبروك مبروووك"},{"id":"2-12","text":"\nمبروك يا ناسنا وأهالينا"},{"id":"2-13","text":"\nيارب كتر أفراحنا"},{"id":"2-14","text":"\nوعلى قد نيتنا إيدينا"}],"title":"مبروك عليكم وعلينا"}]}